htmx_viewsets/VERSION
htmx_viewsets/__init__.py
htmx_viewsets/apps.py
htmx_viewsets/chart.py
htmx_viewsets/color.py
htmx_viewsets/fields.py
htmx_viewsets/forms.py
htmx_viewsets/views.py
htmx_viewsets/viewsets.py
htmx_viewsets/static/bootstrap/5.2.3/bootstrap.min.css
htmx_viewsets/static/bootstrap/5.2.3/bootstrap.min.js
htmx_viewsets/static/datatables/1.13.1/datatables.min.css
htmx_viewsets/static/datatables/1.13.1/datatables.min.js
htmx_viewsets/static/font-awesome/6.4.0/css/all.min.css
htmx_viewsets/static/font-awesome/6.4.0/webfonts/fa-brands-400.ttf
htmx_viewsets/static/font-awesome/6.4.0/webfonts/fa-brands-400.woff2
htmx_viewsets/static/font-awesome/6.4.0/webfonts/fa-regular-400.ttf
htmx_viewsets/static/font-awesome/6.4.0/webfonts/fa-regular-400.woff2
htmx_viewsets/static/font-awesome/6.4.0/webfonts/fa-solid-900.ttf
htmx_viewsets/static/font-awesome/6.4.0/webfonts/fa-solid-900.woff2
htmx_viewsets/static/font-awesome/6.4.0/webfonts/fa-v4compatibility.ttf
htmx_viewsets/static/font-awesome/6.4.0/webfonts/fa-v4compatibility.woff2
htmx_viewsets/static/htmx/1.8.6/htmx.min.js
htmx_viewsets/static/jquery/3.6.4/jquery-3.6.4.min.js
htmx_viewsets/static/select2/4.1.0-rc.0/select2.min.css
htmx_viewsets/static/select2/4.1.0-rc.0/select2.min.js
htmx_viewsets/table/__init__.py
htmx_viewsets/table/action.py
htmx_viewsets/table/cell.py
htmx_viewsets/table/column.py
htmx_viewsets/table/plugins.py
htmx_viewsets/table/row.py
htmx_viewsets/table/table.py
htmx_viewsets/templates/htmx_viewsets/chart.html
htmx_viewsets/templates/htmx_viewsets/delete.html
htmx_viewsets/templates/htmx_viewsets/detail.html
htmx_viewsets/templates/htmx_viewsets/dispatch.html
htmx_viewsets/templates/htmx_viewsets/form.html
htmx_viewsets/templates/htmx_viewsets/full.html
htmx_viewsets/templates/htmx_viewsets/list.html
htmx_viewsets/templates/htmx_viewsets/modal.html
htmx_viewsets/templates/htmx_viewsets/partial.html
htmx_viewsets/templates/htmx_viewsets/table.html
django_htmx_viewsets-0.0.9.dist-info/LICENSE
django_htmx_viewsets-0.0.9.dist-info/METADATA
django_htmx_viewsets-0.0.9.dist-info/WHEEL
django_htmx_viewsets-0.0.9.dist-info/top_level.txt
django_htmx_viewsets-0.0.9.dist-info/RECORD
