Metadata-Version: 2.1
Name: django-htmx-viewsets
Version: 0.0.9
Summary: Viewsets for Django using HTMX, Chartjs and DataTables
Home-page: https://github.com/snake-soft/django-htmx-viewsets
Author: Snake-Soft
Author-email: info@snake-soft.com
License: GPL3
Classifier: Development Status :: 4 - Beta
Classifier: Environment :: Web Environment
Classifier: Framework :: Django
Classifier: Framework :: Django :: 3.0
Classifier: Framework :: Django :: 3.1
Classifier: Framework :: Django :: 3.2
Classifier: Intended Audience :: Developers
Classifier: Operating System :: Unix
Classifier: Programming Language :: Python
Classifier: Programming Language :: Python :: 3
Classifier: Programming Language :: Python :: 3.5
Classifier: Programming Language :: Python :: 3.6
Classifier: Programming Language :: Python :: 3.7
Classifier: Programming Language :: Python :: 3.8
Classifier: Programming Language :: Python :: 3.9
License-File: LICENSE
Requires-Dist: django (<5.0,>=3.2)
Requires-Dist: django-htmx (<2.0.0,>=1.0.0)
Provides-Extra: build
Requires-Dist: django (<5.0,>=3.2) ; extra == 'build'
Requires-Dist: django-htmx (<2.0.0,>=1.0.0) ; extra == 'build'
Requires-Dist: django-debug-toolbar (>=3.8.0) ; extra == 'build'
Requires-Dist: django-extensions (>=3.2.0) ; extra == 'build'
Requires-Dist: psycopg2-binary (>=2.9.0) ; extra == 'build'
Requires-Dist: Werkzeug (>=2.2.0) ; extra == 'build'
Requires-Dist: coverage (>=7.2.0) ; extra == 'build'
Requires-Dist: build (==0.10.0) ; extra == 'build'
Provides-Extra: test
Requires-Dist: django (<5.0,>=3.2) ; extra == 'test'
Requires-Dist: django-htmx (<2.0.0,>=1.0.0) ; extra == 'test'
Requires-Dist: django-debug-toolbar (>=3.8.0) ; extra == 'test'
Requires-Dist: django-extensions (>=3.2.0) ; extra == 'test'
Requires-Dist: psycopg2-binary (>=2.9.0) ; extra == 'test'
Requires-Dist: Werkzeug (>=2.2.0) ; extra == 'test'
Requires-Dist: coverage (>=7.2.0) ; extra == 'test'
